<?xml version="1.0" encoding="UTF-8" ?><document><annotations itct="CAAQwOYBIhMI05m3irSQ3wIVxbOCCh3ZigmoKPgdMgJpdkjjtPSOuaWa6vwB">
<annotation id="annotation_1206506051" type="text" style="popup" log_data="a-type=1&amp;a-id=annotation_1206506051&amp;a-v=_NRpK5HdGmM&amp;ei=LdALXJPPLMXnigTZlabACg&amp;xble=1" itct="CAEQs-UBGP___________wEiEwjTmbeKtJDfAhXFs4IKHdmKCago-B0yAml2SOO09I65pZrq_AE">
  <TEXT>Nuts, 2 coins short of being able to get a 3-star bonus. Oh, well.</TEXT>
  <segment>
    <movingRegion type="rect">
      <rectRegion x="22.66200" y="93.52100" w="57.09300" h="6.62700" t="6:11.000"/>
      <rectRegion x="22.66200" y="93.52100" w="57.09300" h="6.62700" t="6:15.000"/>
    </movingRegion>
  </segment>
  <appearance bgAlpha="0.600000023842" bgColor="0" fgColor="16777215" textSize="3.3098083333333332" effects="">
    
  </appearance>
  
</annotation>
<annotation id="annotation_1325379869" type="text" style="popup" log_data="a-type=1&amp;a-id=annotation_1325379869&amp;a-v=_NRpK5HdGmM&amp;ei=LdALXJPPLMXnigTZlabACg&amp;xble=1" itct="CAIQs-UBGP___________wEiEwjTmbeKtJDfAhXFs4IKHdmKCago-B0yAml2SOO09I65pZrq_AE">
  <TEXT>To be continued... Yo! And, have a Happy Thanksgiving!</TEXT>
  <segment>
    <movingRegion type="rect">
      <rectRegion x="4.27900" y="85.35200" w="49.64400" h="6.90900" t="7:33.000"/>
      <rectRegion x="4.27900" y="85.35200" w="49.64400" h="6.90900" t="7:37.000"/>
    </movingRegion>
  </segment>
  <appearance bgAlpha="0.600000023842" bgColor="0" fgColor="16777215" textSize="3.3098083333333332" effects="">
    
  </appearance>
  
</annotation>
<annotation id="annotation_1482088509" type="text" style="popup" log_data="a-type=1&amp;a-id=annotation_1482088509&amp;a-v=_NRpK5HdGmM&amp;ei=LdALXJPPLMXnigTZlabACg&amp;xble=1" itct="CAMQs-UBGP___________wEiEwjTmbeKtJDfAhXFs4IKHdmKCago-B0yAml2SOO09I65pZrq_AE">
  <TEXT>Next, let&#39;s kill a couple slimes while heading to the right.</TEXT>
  <segment>
    <movingRegion type="rect">
      <rectRegion x="23.61300" y="93.52100" w="50.43600" h="6.62000" t="3:06.000"/>
      <rectRegion x="23.61300" y="93.52100" w="50.43600" h="6.62000" t="3:10.000"/>
    </movingRegion>
  </segment>
  <appearance bgAlpha="0.600000023842" bgColor="0" fgColor="16777215" textSize="3.3098083333333332" effects="">
    
  </appearance>
  
</annotation>
<annotation id="annotation_1502260441" type="text" style="popup" log_data="a-type=1&amp;a-id=annotation_1502260441&amp;a-v=_NRpK5HdGmM&amp;ei=LdALXJPPLMXnigTZlabACg&amp;xble=1" itct="CAQQs-UBGP___________wEiEwjTmbeKtJDfAhXFs4IKHdmKCago-B0yAml2SOO09I65pZrq_AE">
  <TEXT>Yeah, it&#39;s a piece of cake to reach this gem on the second attempt.</TEXT>
  <segment>
    <movingRegion type="rect">
      <rectRegion x="20.12700" y="93.52100" w="59.31200" h="6.62700" t="5:04.500"/>
      <rectRegion x="20.12700" y="93.52100" w="59.31200" h="6.62700" t="5:08.500"/>
    </movingRegion>
  </segment>
  <appearance bgAlpha="0.600000023842" bgColor="0" fgColor="16777215" textSize="3.3098083333333332" effects="">
    
  </appearance>
  
</annotation>
<annotation id="annotation_1524261087" type="text" style="popup" log_data="a-type=1&amp;a-id=annotation_1524261087&amp;a-v=_NRpK5HdGmM&amp;ei=LdALXJPPLMXnigTZlabACg&amp;xble=1" itct="CAUQs-UBGP___________wEiEwjTmbeKtJDfAhXFs4IKHdmKCago-B0yAml2SOO09I65pZrq_AE">
  <TEXT>Whoa, hello! That particular shooter was in possession of the second gem! (Well, more like he was overlapping the gem, but it&#39;s essentially the same thing.)</TEXT>
  <segment>
    <movingRegion type="rect">
      <rectRegion x="13.78800" y="89.29600" w="71.83100" h="10.85200" t="1:08.500"/>
      <rectRegion x="13.78800" y="89.29600" w="71.83100" h="10.85200" t="1:14.500"/>
    </movingRegion>
  </segment>
  <appearance bgAlpha="0.600000023842" bgColor="0" fgColor="16777215" textSize="3.3098083333333332" effects="">
    
  </appearance>
  
</annotation>
<annotation id="annotation_1540556511" type="text" style="popup" log_data="a-type=1&amp;a-id=annotation_1540556511&amp;a-v=_NRpK5HdGmM&amp;ei=LdALXJPPLMXnigTZlabACg&amp;xble=1" itct="CAYQs-UBGP___________wEiEwjTmbeKtJDfAhXFs4IKHdmKCago-B0yAml2SOO09I65pZrq_AE">
  <TEXT>Now, the last gem involves this red timer switch. Beware, as you only get one chance, and it only lasts 10 seconds.</TEXT>
  <segment>
    <movingRegion type="rect">
      <rectRegion x="24.56400" y="89.01400" w="51.70500" h="11.13400" t="5:09.012"/>
      <rectRegion x="24.56400" y="89.01400" w="51.70500" h="11.13400" t="5:15.000"/>
    </movingRegion>
  </segment>
  <appearance bgAlpha="0.600000023842" bgColor="0" fgColor="16777215" textSize="3.3098083333333332" effects="">
    
  </appearance>
  
</annotation>
<annotation id="annotation_1662977399" type="text" style="popup" log_data="a-type=1&amp;a-id=annotation_1662977399&amp;a-v=_NRpK5HdGmM&amp;ei=LdALXJPPLMXnigTZlabACg&amp;xble=1" itct="CAcQs-UBGP___________wEiEwjTmbeKtJDfAhXFs4IKHdmKCago-B0yAml2SOO09I65pZrq_AE">
  <TEXT>So, place your votes for either 4-4 (Laser Workshop) or 4-A (Gigantic Nightmare)!</TEXT>
  <segment>
    <movingRegion type="rect">
      <rectRegion x="13.62900" y="93.52100" w="71.83100" h="6.62700" t="6:34.500"/>
      <rectRegion x="13.62900" y="93.52100" w="71.83100" h="6.62700" t="6:39.500"/>
    </movingRegion>
  </segment>
  <appearance bgAlpha="0.600000023842" bgColor="0" fgColor="16777215" textSize="3.3098083333333332" effects="">
    
  </appearance>
  
</annotation>
<annotation id="annotation_1761627719" type="text" style="popup" log_data="a-type=1&amp;a-id=annotation_1761627719&amp;a-v=_NRpK5HdGmM&amp;ei=LdALXJPPLMXnigTZlabACg&amp;xble=1" itct="CAgQs-UBGP___________wEiEwjTmbeKtJDfAhXFs4IKHdmKCago-B0yAml2SOO09I65pZrq_AE">
  <TEXT>The yellow switch can be ignored, but you do need to hit the blue switch on your way up.</TEXT>
  <segment>
    <movingRegion type="rect">
      <rectRegion x="29.79400" y="89.29600" w="40.61100" h="10.85200" t="6:50.000"/>
      <rectRegion x="29.79400" y="89.29600" w="40.61100" h="10.85200" t="6:55.000"/>
    </movingRegion>
  </segment>
  <appearance bgAlpha="0.600000023842" bgColor="0" fgColor="16777215" textSize="3.3098083333333332" effects="">
    
  </appearance>
  
</annotation>
<annotation id="annotation_182622077" type="text" style="popup" log_data="a-type=1&amp;a-id=annotation_182622077&amp;a-v=_NRpK5HdGmM&amp;ei=LdALXJPPLMXnigTZlabACg&amp;xble=1" itct="CAkQs-UBGP___________wEiEwjTmbeKtJDfAhXFs4IKHdmKCago-B0yAml2SOO09I65pZrq_AE">
  <TEXT>Hit this switch, slide these bars outta the way, hit the green gate switch, then go down and finish.</TEXT>
  <segment>
    <movingRegion type="rect">
      <rectRegion x="28.84300" y="89.29600" w="44.25600" h="10.85200" t="7:10.000"/>
      <rectRegion x="28.84300" y="89.29600" w="44.25600" h="10.85200" t="7:15.000"/>
    </movingRegion>
  </segment>
  <appearance bgAlpha="0.600000023842" bgColor="0" fgColor="16777215" textSize="3.3098083333333332" effects="">
    
  </appearance>
  
</annotation>
<annotation id="annotation_1943862221" type="text" style="popup" log_data="a-type=1&amp;a-id=annotation_1943862221&amp;a-v=_NRpK5HdGmM&amp;ei=LdALXJPPLMXnigTZlabACg&amp;xble=1" itct="CAoQs-UBGP___________wEiEwjTmbeKtJDfAhXFs4IKHdmKCago-B0yAml2SOO09I65pZrq_AE">
  <TEXT>And here, we have to hit an orange timer switch, and go all the way around the level horizontally (yep, this level wraps) to reach the timer gate within 12 seconds.</TEXT>
  <segment>
    <movingRegion type="rect">
      <rectRegion x="14.10500" y="89.29600" w="72.30700" h="10.85200" t="3:10.500"/>
      <rectRegion x="14.10500" y="89.29600" w="72.30700" h="10.85200" t="3:16.500"/>
    </movingRegion>
  </segment>
  <appearance bgAlpha="0.600000023842" bgColor="0" fgColor="16777215" textSize="3.3098083333333332" effects="">
    
  </appearance>
  
</annotation>
<annotation id="annotation_1983885619" type="text" style="popup" log_data="a-type=1&amp;a-id=annotation_1983885619&amp;a-v=_NRpK5HdGmM&amp;ei=LdALXJPPLMXnigTZlabACg&amp;xble=1" itct="">
  <TEXT>Now, to end off this episode, I&#39;ll Time Attack 1-9 with Daria.</TEXT>
  <segment>
    <movingRegion type="rect">
      <rectRegion x="23.29600" y="93.23900" w="52.65600" h="6.90900" t="6:40.000"/>
      <rectRegion x="23.29600" y="93.23900" w="52.65600" h="6.90900" t="6:44.000"/>
    </movingRegion>
  </segment>
  <appearance bgAlpha="0.600000023842" bgColor="0" fgColor="16777215" textSize="3.3098083333333332" effects="">
    
  </appearance>
  
</annotation>
<annotation id="annotation_2003590455" type="text" style="popup" log_data="a-type=1&amp;a-id=annotation_2003590455&amp;a-v=_NRpK5HdGmM&amp;ei=LdALXJPPLMXnigTZlabACg&amp;xble=1" itct="">
  <TEXT>Hello, and welcome back to Miracle Fly! Okay, so let&#39;s see those votes...</TEXT>
  <segment>
    <movingRegion type="rect">
      <rectRegion x="18.54200" y="93.52100" w="63.90700" h="6.62700" t="0:01.000"/>
      <rectRegion x="18.54200" y="93.52100" w="63.90700" h="6.62700" t="0:05.000"/>
    </movingRegion>
  </segment>
  <appearance bgAlpha="0.600000023842" bgColor="0" fgColor="16777215" textSize="3.3098083333333332" effects="">
    
  </appearance>
  
</annotation>
<annotation id="annotation_2102355211" type="text" style="popup" log_data="a-type=1&amp;a-id=annotation_2102355211&amp;a-v=_NRpK5HdGmM&amp;ei=LdALXJPPLMXnigTZlabACg&amp;xble=1" itct="">
  <TEXT>Okay, the first thing you will probably want to do here is destroy the shooter to the left of the yellow switch, before actually hitting the switch.</TEXT>
  <segment>
    <movingRegion type="rect">
      <rectRegion x="20.91900" y="89.29600" w="63.43200" h="10.84500" t="0:20.000"/>
      <rectRegion x="20.91900" y="89.29600" w="63.43200" h="10.84500" t="0:26.000"/>
    </movingRegion>
  </segment>
  <appearance bgAlpha="0.600000023842" bgColor="0" fgColor="16777215" textSize="3.3098083333333332" effects="">
    
  </appearance>
  
</annotation>
<annotation id="annotation_2124606451" type="text" style="popup" log_data="a-type=1&amp;a-id=annotation_2124606451&amp;a-v=_NRpK5HdGmM&amp;ei=LdALXJPPLMXnigTZlabACg&amp;xble=1" itct="">
  <TEXT>In here, slay the slimes as usual, and hit the green switch. Now, if you&#39;re fast enough, you may actually be able to reach the 2nd gem with what&#39;s left of that 24-second timer. Can I do it?</TEXT>
  <segment>
    <movingRegion type="rect">
      <rectRegion x="9.35000" y="89.29600" w="83.24200" h="10.85200" t="4:34.991"/>
      <rectRegion x="9.35000" y="89.29600" w="83.24200" h="10.85200" t="4:42.000"/>
    </movingRegion>
  </segment>
  <appearance bgAlpha="0.600000023842" bgColor="0" fgColor="16777215" textSize="3.3098083333333332" effects="">
    
  </appearance>
  
</annotation>
<annotation id="annotation_2224966233" type="text" style="popup" log_data="a-type=1&amp;a-id=annotation_2224966233&amp;a-v=_NRpK5HdGmM&amp;ei=LdALXJPPLMXnigTZlabACg&amp;xble=1" itct="">
  <TEXT>Alright, that unlocked 4-4. And, we still have 4-A just to the left.</TEXT>
  <segment>
    <movingRegion type="rect">
      <rectRegion x="22.82100" y="93.23900" w="55.03300" h="6.90900" t="6:24.000"/>
      <rectRegion x="22.82100" y="93.23900" w="55.03300" h="6.90900" t="6:28.000"/>
    </movingRegion>
  </segment>
  <appearance bgAlpha="0.600000023842" bgColor="0" fgColor="16777215" textSize="3.3098083333333332" effects="">
    
  </appearance>
  
</annotation>
<annotation id="annotation_2322331457" type="text" style="popup" log_data="a-type=1&amp;a-id=annotation_2322331457&amp;a-v=_NRpK5HdGmM&amp;ei=LdALXJPPLMXnigTZlabACg&amp;xble=1" itct="">
  <TEXT>And with that, this level is done. Unfortunately, I&#39;m unable to line up my coins for a 3-star bonus here. Oh, well.</TEXT>
  <segment>
    <movingRegion type="rect">
      <rectRegion x="23.93000" y="89.01400" w="51.07100" h="11.13400" t="1:54.500"/>
      <rectRegion x="23.93000" y="89.01400" w="51.07100" h="11.13400" t="2:00.500"/>
    </movingRegion>
  </segment>
  <appearance bgAlpha="0.600000023842" bgColor="0" fgColor="16777215" textSize="3.3098083333333332" effects="">
    
  </appearance>
  
</annotation>
<annotation id="annotation_2381522835" type="text" style="popup" log_data="a-type=1&amp;a-id=annotation_2381522835&amp;a-v=_NRpK5HdGmM&amp;ei=LdALXJPPLMXnigTZlabACg&amp;xble=1" itct="">
  <TEXT>Triple combo!
(3 kills, 3000 points)</TEXT>
  <segment>
    <movingRegion type="rect">
      <rectRegion x="80.19000" y="12.95800" w="19.85000" h="11.13400" t="1:15.000"/>
      <rectRegion x="80.19000" y="12.95800" w="19.85000" h="11.13400" t="1:19.000"/>
    </movingRegion>
  </segment>
  <appearance bgAlpha="0.600000023842" bgColor="0" fgColor="16777215" textSize="3.3098083333333332" effects="">
    
  </appearance>
  
</annotation>
<annotation id="annotation_2466183631" type="text" style="popup" log_data="a-type=1&amp;a-id=annotation_2466183631&amp;a-v=_NRpK5HdGmM&amp;ei=LdALXJPPLMXnigTZlabACg&amp;xble=1" itct="">
  <TEXT>MOOOONNNSSS!!! Yeah, so I believe this is the first level that has four different colors for the standard colored gates, and the fourth one is purple, with the moon symbol.</TEXT>
  <segment>
    <movingRegion type="rect">
      <rectRegion x="12.36100" y="89.29600" w="75.95200" h="10.85200" t="3:39.450"/>
      <rectRegion x="12.36100" y="89.29600" w="75.95200" h="10.85200" t="3:46.500"/>
    </movingRegion>
  </segment>
  <appearance bgAlpha="0.600000023842" bgColor="0" fgColor="16777215" textSize="3.3098083333333332" effects="">
    
  </appearance>
  
</annotation>
<annotation id="annotation_2468488251" type="text" style="popup" log_data="a-type=1&amp;a-id=annotation_2468488251&amp;a-v=_NRpK5HdGmM&amp;ei=LdALXJPPLMXnigTZlabACg&amp;xble=1" itct="">
  <TEXT>...then we can talk about parallel universes! ...Yeah, you can see the bottom of the level, since it wraps vertically as well. (Fortunately, this didn&#39;t require building up QPU speed for over 12 hours or something ridiculous like that!)</TEXT>
  <segment>
    <movingRegion type="rect">
      <rectRegion x="0.00000" y="89.29600" w="100.00000" h="10.84500" t="5:57.000"/>
      <rectRegion x="0.00000" y="89.29600" w="100.00000" h="10.84500" t="6:05.000"/>
    </movingRegion>
  </segment>
  <appearance bgAlpha="0.600000023842" bgColor="0" fgColor="16777215" textSize="3.3098083333333332" effects="">
    
  </appearance>
  
</annotation>
<annotation id="annotation_2501356137" type="text" style="popup" log_data="a-type=1&amp;a-id=annotation_2501356137&amp;a-v=_NRpK5HdGmM&amp;ei=LdALXJPPLMXnigTZlabACg&amp;xble=1" itct="">
  <TEXT>Alright, let&#39;s get outta here.</TEXT>
  <segment>
    <movingRegion type="rect">
      <rectRegion x="37.87600" y="93.52100" w="24.92200" h="6.62700" t="6:05.500"/>
      <rectRegion x="37.87600" y="93.52100" w="24.92200" h="6.62700" t="6:09.500"/>
    </movingRegion>
  </segment>
  <appearance bgAlpha="0.600000023842" bgColor="0" fgColor="16777215" textSize="3.3098083333333332" effects="">
    
  </appearance>
  
</annotation>
<annotation id="annotation_2611804507" type="text" style="popup" log_data="a-type=1&amp;a-id=annotation_2611804507&amp;a-v=_NRpK5HdGmM&amp;ei=LdALXJPPLMXnigTZlabACg&amp;xble=1" itct="">
  <TEXT>Oh, and don&#39;t worry about the coins I skipped there. I&#39;ll be getting them later.</TEXT>
  <segment>
    <movingRegion type="rect">
      <rectRegion x="17.59100" y="93.52100" w="67.39400" h="6.62700" t="4:02.500"/>
      <rectRegion x="17.59100" y="93.52100" w="67.39400" h="6.62700" t="4:06.500"/>
    </movingRegion>
  </segment>
  <appearance bgAlpha="0.600000023842" bgColor="0" fgColor="16777215" textSize="3.3098083333333332" effects="">
    
  </appearance>
  
</annotation>
<annotation id="annotation_2706409293" type="text" style="popup" log_data="a-type=1&amp;a-id=annotation_2706409293&amp;a-v=_NRpK5HdGmM&amp;ei=LdALXJPPLMXnigTZlabACg&amp;xble=1" itct="">
  <TEXT>D&#39;oh! If only I didn&#39;t get hung up on that corner... But, that&#39;s okay. If you don&#39;t make it there, just go down here and hit the 24-second timer switch again. It should be much easier to make it this time.</TEXT>
  <segment>
    <movingRegion type="rect">
      <rectRegion x="6.65600" y="89.29600" w="86.88700" h="10.85200" t="4:47.956"/>
      <rectRegion x="6.65600" y="89.29600" w="86.88700" h="10.85200" t="4:55.000"/>
    </movingRegion>
  </segment>
  <appearance bgAlpha="0.600000023842" bgColor="0" fgColor="16777215" textSize="3.3098083333333332" effects="">
    
  </appearance>
  
</annotation>
<annotation id="annotation_2720768347" type="text" style="popup" log_data="a-type=1&amp;a-id=annotation_2720768347&amp;a-v=_NRpK5HdGmM&amp;ei=LdALXJPPLMXnigTZlabACg&amp;xble=1" itct="">
  <TEXT>Okay, one gem left to go, and to reach it, you gotta win another race. This race starts when you hit the blue switch down here. Also, in case you&#39;re hurting from the first race, there&#39;s a health potion above the blue switch.</TEXT>
  <segment>
    <movingRegion type="rect">
      <rectRegion x="1.58500" y="11.83100" w="96.98900" h="10.84500" t="1:22.500"/>
      <rectRegion x="1.58500" y="11.83100" w="96.98900" h="10.84500" t="1:30.500"/>
    </movingRegion>
  </segment>
  <appearance bgAlpha="0.600000023842" bgColor="0" fgColor="16777215" textSize="3.3098083333333332" effects="">
    
  </appearance>
  
</annotation>
<annotation id="annotation_2723291827" type="text" style="popup" log_data="a-type=1&amp;a-id=annotation_2723291827&amp;a-v=_NRpK5HdGmM&amp;ei=LdALXJPPLMXnigTZlabACg&amp;xble=1" itct="">
  <TEXT>It&#39;s okay to go for these coins in the upper alcoves here, since 24 seconds is way more than enough time. Also, we will be getting to both of those gems eventually.</TEXT>
  <segment>
    <movingRegion type="rect">
      <rectRegion x="16.32300" y="89.01400" w="72.30700" h="11.13400" t="4:28.500"/>
      <rectRegion x="16.32300" y="89.01400" w="72.30700" h="11.13400" t="4:34.500"/>
    </movingRegion>
  </segment>
  <appearance bgAlpha="0.600000023842" bgColor="0" fgColor="16777215" textSize="3.3098083333333332" effects="">
    
  </appearance>
  
</annotation>
<annotation id="annotation_2767694037" type="text" style="popup" log_data="a-type=1&amp;a-id=annotation_2767694037&amp;a-v=_NRpK5HdGmM&amp;ei=LdALXJPPLMXnigTZlabACg&amp;xble=1" itct="">
  <TEXT>Then, hit this timer switch, and race to the right to get through a timer gate within 12 seconds. Don&#39;t be too reckless, though, due to all the spikes. 12 seconds is plenty of time for this.</TEXT>
  <segment>
    <movingRegion type="rect">
      <rectRegion x="9.35000" y="89.29600" w="82.13300" h="10.85200" t="3:55.000"/>
      <rectRegion x="9.35000" y="89.29600" w="82.13300" h="10.85200" t="4:02.000"/>
    </movingRegion>
  </segment>
  <appearance bgAlpha="0.600000023842" bgColor="0" fgColor="16777215" textSize="3.3098083333333332" effects="">
    
  </appearance>
  
</annotation>
<annotation id="annotation_2861037421" type="text" style="popup" log_data="a-type=1&amp;a-id=annotation_2861037421&amp;a-v=_NRpK5HdGmM&amp;ei=LdALXJPPLMXnigTZlabACg&amp;xble=1" itct="">
  <TEXT>...Yep, it&#39;s single-use only, vanishing entirely after it expires. This means you only get one shot at getting through the red timer gate, and if you blow it, you&#39;ll have to restart the level for another chance.</TEXT>
  <segment>
    <movingRegion type="rect">
      <rectRegion x="5.70500" y="89.29600" w="88.94700" h="10.85200" t="2:44.517"/>
      <rectRegion x="5.70500" y="89.29600" w="88.94700" h="10.85200" t="2:51.500"/>
    </movingRegion>
  </segment>
  <appearance bgAlpha="0.600000023842" bgColor="0" fgColor="16777215" textSize="3.3098083333333332" effects="">
    
  </appearance>
  
</annotation>
<annotation id="annotation_3015221705" type="text" style="popup" log_data="a-type=1&amp;a-id=annotation_3015221705&amp;a-v=_NRpK5HdGmM&amp;ei=LdALXJPPLMXnigTZlabACg&amp;xble=1" itct="">
  <TEXT>BTW, if you wanted, you could leave the first shooter that was to the left of the yellow switch alive at first, in order to later include him in the combo with the others.</TEXT>
  <segment>
    <movingRegion type="rect">
      <rectRegion x="13.15400" y="89.29600" w="74.20900" h="10.85200" t="1:15.000"/>
      <rectRegion x="13.15400" y="89.29600" w="74.20900" h="10.85200" t="1:21.000"/>
    </movingRegion>
  </segment>
  <appearance bgAlpha="0.600000023842" bgColor="0" fgColor="16777215" textSize="3.3098083333333332" effects="">
    
  </appearance>
  
</annotation>
<annotation id="annotation_3036567615" type="text" style="popup" log_data="a-type=1&amp;a-id=annotation_3036567615&amp;a-v=_NRpK5HdGmM&amp;ei=LdALXJPPLMXnigTZlabACg&amp;xble=1" itct="">
  <TEXT>Fortunately, this red timer switch is right at the start of the level, so there&#39;s not much to lose if you screw this one up.</TEXT>
  <segment>
    <movingRegion type="rect">
      <rectRegion x="23.61300" y="89.29600" w="51.86300" h="10.85200" t="2:52.000"/>
      <rectRegion x="23.61300" y="89.29600" w="51.86300" h="10.85200" t="2:58.000"/>
    </movingRegion>
  </segment>
  <appearance bgAlpha="0.600000023842" bgColor="0" fgColor="16777215" textSize="3.3098083333333332" effects="">
    
  </appearance>
  
</annotation>
<annotation id="annotation_307373259" type="text" style="popup" log_data="a-type=1&amp;a-id=annotation_307373259&amp;a-v=_NRpK5HdGmM&amp;ei=LdALXJPPLMXnigTZlabACg&amp;xble=1" itct="">
  <TEXT>Don&#39;t worry about killing these guys or taking a couple hits during the race! Just move! We can come back and deal with them later.</TEXT>
  <segment>
    <movingRegion type="rect">
      <rectRegion x="19.49300" y="11.54900" w="58.20200" h="10.85200" t="0:33.488"/>
      <rectRegion x="19.49300" y="11.54900" w="58.20200" h="10.85200" t="0:39.500"/>
    </movingRegion>
  </segment>
  <appearance bgAlpha="0.600000023842" bgColor="0" fgColor="16777215" textSize="3.3098083333333332" effects="">
    
  </appearance>
  
</annotation>
<annotation id="annotation_3220006451" type="text" style="popup" log_data="a-type=1&amp;a-id=annotation_3220006451&amp;a-v=_NRpK5HdGmM&amp;ei=LdALXJPPLMXnigTZlabACg&amp;xble=1" itct="">
  <TEXT>Now, while this may look complicated, it&#39;s really not that bad once you start working your way through it. First, hit the yellow switch over here, since that&#39;s the only way to begin this part.</TEXT>
  <segment>
    <movingRegion type="rect">
      <rectRegion x="9.98400" y="89.29600" w="81.81600" h="10.85200" t="3:47.012"/>
      <rectRegion x="9.98400" y="89.29600" w="81.81600" h="10.85200" t="3:54.000"/>
    </movingRegion>
  </segment>
  <appearance bgAlpha="0.600000023842" bgColor="0" fgColor="16777215" textSize="3.3098083333333332" effects="">
    
  </appearance>
  
</annotation>
<annotation id="annotation_3247069423" type="text" style="popup" log_data="a-type=1&amp;a-id=annotation_3247069423&amp;a-v=_NRpK5HdGmM&amp;ei=LdALXJPPLMXnigTZlabACg&amp;xble=1" itct="">
  <TEXT>Okay, I&#39;m gonna go over here and quickly add a couple of stationary black slimes to my current combo, since I can easily do so.</TEXT>
  <segment>
    <movingRegion type="rect">
      <rectRegion x="20.28500" y="89.29600" w="59.94600" h="10.85200" t="3:25.472"/>
      <rectRegion x="20.28500" y="89.29600" w="59.94600" h="10.85200" t="3:31.500"/>
    </movingRegion>
  </segment>
  <appearance bgAlpha="0.600000023842" bgColor="0" fgColor="16777215" textSize="3.3098083333333332" effects="">
    
  </appearance>
  
</annotation>
<annotation id="annotation_328443775" type="text" style="popup" log_data="a-type=1&amp;a-id=annotation_328443775&amp;a-v=_NRpK5HdGmM&amp;ei=LdALXJPPLMXnigTZlabACg&amp;xble=1" itct="">
  <TEXT>Super combo!
(4 kills, 5000 points)</TEXT>
  <segment>
    <movingRegion type="rect">
      <rectRegion x="80.19000" y="13.23900" w="19.85000" h="10.85200" t="4:39.500"/>
      <rectRegion x="80.19000" y="13.23900" w="19.85000" h="10.85200" t="4:43.500"/>
    </movingRegion>
  </segment>
  <appearance bgAlpha="0.600000023842" bgColor="0" fgColor="16777215" textSize="3.3098083333333332" effects="">
    
  </appearance>
  
</annotation>
<annotation id="annotation_3386624443" type="text" style="popup" log_data="a-type=1&amp;a-id=annotation_3386624443&amp;a-v=_NRpK5HdGmM&amp;ei=LdALXJPPLMXnigTZlabACg&amp;xble=1" itct="">
  <TEXT>Oh, I want to go down this way this time. Also, don&#39;t hit the yellow switch this time, or you&#39;ll lose a chunk of progress and have to redo some steps.</TEXT>
  <segment>
    <movingRegion type="rect">
      <rectRegion x="17.90800" y="89.29600" w="65.65000" h="10.84500" t="4:58.000"/>
      <rectRegion x="17.90800" y="89.29600" w="65.65000" h="10.84500" t="5:04.000"/>
    </movingRegion>
  </segment>
  <appearance bgAlpha="0.600000023842" bgColor="0" fgColor="16777215" textSize="3.3098083333333332" effects="">
    
  </appearance>
  
</annotation>
<annotation id="annotation_3639133397" type="text" style="popup" log_data="a-type=1&amp;a-id=annotation_3639133397&amp;a-v=_NRpK5HdGmM&amp;ei=LdALXJPPLMXnigTZlabACg&amp;xble=1" itct="">
  <TEXT>Slay a couple black slimes here, and hit the blue switch.</TEXT>
  <segment>
    <movingRegion type="rect">
      <rectRegion x="23.77200" y="93.52100" w="50.59500" h="6.62700" t="4:12.500"/>
      <rectRegion x="23.77200" y="93.52100" w="50.59500" h="6.62700" t="4:16.500"/>
    </movingRegion>
  </segment>
  <appearance bgAlpha="0.600000023842" bgColor="0" fgColor="16777215" textSize="3.3098083333333332" effects="">
    
  </appearance>
  
</annotation>
<annotation id="annotation_3640513821" type="text" style="popup" log_data="a-type=1&amp;a-id=annotation_3640513821&amp;a-v=_NRpK5HdGmM&amp;ei=LdALXJPPLMXnigTZlabACg&amp;xble=1" itct="">
  <TEXT>☾ush!</TEXT>
  <segment>
    <movingRegion type="rect">
      <rectRegion x="46.59300" y="68.73200" w="8.28100" h="6.62700" t="5:29.500"/>
      <rectRegion x="46.59300" y="68.73200" w="8.28100" h="6.62700" t="5:31.000"/>
    </movingRegion>
  </segment>
  <appearance bgAlpha="0.600000023842" bgColor="0" fgColor="16777215" textSize="3.3098083333333332" effects="">
    
  </appearance>
  
</annotation>
<annotation id="annotation_3674005903" type="text" style="popup" log_data="a-type=1&amp;a-id=annotation_3674005903&amp;a-v=_NRpK5HdGmM&amp;ei=LdALXJPPLMXnigTZlabACg&amp;xble=1" itct="">
  <TEXT>Alright, Irvette, let&#39;s race for candy!</TEXT>
  <segment>
    <movingRegion type="rect">
      <rectRegion x="0.00000" y="93.52100" w="31.26100" h="6.62700" t="0:12.000"/>
      <rectRegion x="0.00000" y="93.52100" w="31.26100" h="6.62700" t="0:16.000"/>
    </movingRegion>
  </segment>
  <appearance bgAlpha="0.600000023842" bgColor="0" fgColor="16777215" textSize="3.3098083333333332" effects="">
    
  </appearance>
  
</annotation>
<annotation id="annotation_3675715671" type="text" style="popup" log_data="a-type=1&amp;a-id=annotation_3675715671&amp;a-v=_NRpK5HdGmM&amp;ei=LdALXJPPLMXnigTZlabACg&amp;xble=1" itct="">
  <TEXT>There&#39;s a couple strips of chocolate here which slow you down slightly, but they also help your mana supply a bit as you pass through them, which is nice. And, then down below, no need to kill the shooters. Just go!</TEXT>
  <segment>
    <movingRegion type="rect">
      <rectRegion x="2.53600" y="11.54900" w="94.96800" h="10.84500" t="1:38.000"/>
      <rectRegion x="2.53600" y="11.54900" w="94.96800" h="10.84500" t="1:46.000"/>
    </movingRegion>
  </segment>
  <appearance bgAlpha="0.600000023842" bgColor="0" fgColor="16777215" textSize="3.3098083333333332" effects="">
    
  </appearance>
  
</annotation>
<annotation id="annotation_3724373281" type="text" style="popup" log_data="a-type=1&amp;a-id=annotation_3724373281&amp;a-v=_NRpK5HdGmM&amp;ei=LdALXJPPLMXnigTZlabACg&amp;xble=1" itct="">
  <TEXT>Final gem get! Oh, and since I&#39;m using Mira while outside of one of these large world 4 levels this time, I guess I can show you guys this.</TEXT>
  <segment>
    <movingRegion type="rect">
      <rectRegion x="19.17600" y="89.29600" w="62.00600" h="10.85200" t="5:41.500"/>
      <rectRegion x="19.17600" y="89.29600" w="62.00600" h="10.85200" t="5:47.500"/>
    </movingRegion>
  </segment>
  <appearance bgAlpha="0.600000023842" bgColor="0" fgColor="16777215" textSize="3.3098083333333332" effects="">
    
  </appearance>
  
</annotation>
<annotation id="annotation_3761473695" type="text" style="popup" log_data="a-type=1&amp;a-id=annotation_3761473695&amp;a-v=_NRpK5HdGmM&amp;ei=LdALXJPPLMXnigTZlabACg&amp;xble=1" itct="">
  <TEXT>It&#39;s not all that hard, but the bat enemy tends to get in the way, so try to have enough time to deal with him too. And fortunately, if you don&#39;t get through the timer gate in time, you can just try again, since it&#39;s orange.</TEXT>
  <segment>
    <movingRegion type="rect">
      <rectRegion x="3.48700" y="89.29600" w="92.75000" h="10.84500" t="3:17.000"/>
      <rectRegion x="3.48700" y="89.29600" w="92.75000" h="10.84500" t="3:25.000"/>
    </movingRegion>
  </segment>
  <appearance bgAlpha="0.600000023842" bgColor="0" fgColor="16777215" textSize="3.3098083333333332" effects="">
    
  </appearance>
  
</annotation>
<annotation id="annotation_3781075031" type="text" style="popup" log_data="a-type=1&amp;a-id=annotation_3781075031&amp;a-v=_NRpK5HdGmM&amp;ei=LdALXJPPLMXnigTZlabACg&amp;xble=1" itct="">
  <TEXT>If you fly upwards for long enough...</TEXT>
  <segment>
    <movingRegion type="rect">
      <rectRegion x="33.28100" y="93.52100" w="32.68600" h="6.62000" t="5:47.972"/>
      <rectRegion x="33.28100" y="93.52100" w="32.68600" h="6.62000" t="5:52.000"/>
    </movingRegion>
  </segment>
  <appearance bgAlpha="0.600000023842" bgColor="0" fgColor="16777215" textSize="3.3098083333333332" effects="">
    
  </appearance>
  
</annotation>
<annotation id="annotation_3808887293" type="text" style="popup" log_data="a-type=1&amp;a-id=annotation_3808887293&amp;a-v=_NRpK5HdGmM&amp;ei=LdALXJPPLMXnigTZlabACg&amp;xble=1" itct="">
  <TEXT>I could&#39;ve tried for a bigger combo, but whatever. Also, I&#39;ll be grabbing all of the enemy-dropped coins here, because eventually, I won&#39;t be able to come back to this part of the level.</TEXT>
  <segment>
    <movingRegion type="rect">
      <rectRegion x="8.55800" y="88.73200" w="83.71600" h="11.40800" t="0:56.000"/>
      <rectRegion x="8.55800" y="88.73200" w="83.71600" h="11.40800" t="1:03.000"/>
    </movingRegion>
  </segment>
  <appearance bgAlpha="0.600000023842" bgColor="0" fgColor="16777215" textSize="3.3098083333333332" effects="">
    
  </appearance>
  
</annotation>
<annotation id="annotation_388133163" type="text" style="popup" log_data="a-type=1&amp;a-id=annotation_388133163&amp;a-v=_NRpK5HdGmM&amp;ei=LdALXJPPLMXnigTZlabACg&amp;xble=1" itct="">
  <TEXT>It&#39;s gonna be close...</TEXT>
  <segment>
    <movingRegion type="rect">
      <rectRegion x="40.88700" y="93.52100" w="20.00900" h="6.62700" t="4:43.000"/>
      <rectRegion x="40.88700" y="93.52100" w="20.00900" h="6.62700" t="4:46.000"/>
    </movingRegion>
  </segment>
  <appearance bgAlpha="0.600000023842" bgColor="0" fgColor="16777215" textSize="3.3098083333333332" effects="">
    
  </appearance>
  
</annotation>
<annotation id="annotation_3887027893" type="text" style="popup" log_data="a-type=1&amp;a-id=annotation_3887027893&amp;a-v=_NRpK5HdGmM&amp;ei=LdALXJPPLMXnigTZlabACg&amp;xble=1" itct="">
  <TEXT>Alright, and with the purple moon switch pressed, we can now fly outside of the confines of the level and grab the last gem!</TEXT>
  <segment>
    <movingRegion type="rect">
      <rectRegion x="20.91900" y="89.29600" w="55.98400" h="10.85200" t="5:31.500"/>
      <rectRegion x="20.91900" y="89.29600" w="55.98400" h="10.85200" t="5:37.500"/>
    </movingRegion>
  </segment>
  <appearance bgAlpha="0.600000023842" bgColor="0" fgColor="16777215" textSize="3.3098083333333332" effects="">
    
  </appearance>
  
</annotation>
<annotation id="annotation_398310503" type="text" style="popup" log_data="a-type=1&amp;a-id=annotation_398310503&amp;a-v=_NRpK5HdGmM&amp;ei=LdALXJPPLMXnigTZlabACg&amp;xble=1" itct="">
  <TEXT>I could&#39;ve tried to extend the combo further, but it would probably require a lot of split-second rests, and I don&#39;t want to take all day here. So, let&#39;s take a look around this place...</TEXT>
  <segment>
    <movingRegion type="rect">
      <rectRegion x="9.82600" y="89.01400" w="81.64800" h="11.11300" t="3:32.000"/>
      <rectRegion x="9.82600" y="89.01400" w="81.64800" h="11.11300" t="3:39.000"/>
    </movingRegion>
  </segment>
  <appearance bgAlpha="0.600000023842" bgColor="0" fgColor="16777215" textSize="3.3098083333333332" effects="">
    
  </appearance>
  
</annotation>
<annotation id="annotation_4030710875" type="text" style="popup" log_data="a-type=1&amp;a-id=annotation_4030710875&amp;a-v=_NRpK5HdGmM&amp;ei=LdALXJPPLMXnigTZlabACg&amp;xble=1" itct="">
  <TEXT>Now, 5 seconds isn&#39;t very much time to make this hairpin turn and reach the gem, so it might take you a few tries, but you can just keep restarting the level until you make it.</TEXT>
  <segment>
    <movingRegion type="rect">
      <rectRegion x="12.52000" y="89.29600" w="75.95100" h="10.84500" t="2:58.500"/>
      <rectRegion x="12.52000" y="89.29600" w="75.95100" h="10.84500" t="3:05.500"/>
    </movingRegion>
  </segment>
  <appearance bgAlpha="0.600000023842" bgColor="0" fgColor="16777215" textSize="3.3098083333333332" effects="">
    
  </appearance>
  
</annotation>
<annotation id="annotation_4046560515" type="text" style="popup" log_data="a-type=1&amp;a-id=annotation_4046560515&amp;a-v=_NRpK5HdGmM&amp;ei=LdALXJPPLMXnigTZlabACg&amp;xble=1" itct="">
  <TEXT>And, the race is on!</TEXT>
  <segment>
    <movingRegion type="rect">
      <rectRegion x="41.36300" y="93.52100" w="18.74100" h="6.62700" t="1:34.535"/>
      <rectRegion x="41.36300" y="93.52100" w="18.74100" h="6.62700" t="1:37.500"/>
    </movingRegion>
  </segment>
  <appearance bgAlpha="0.600000023842" bgColor="0" fgColor="16777215" textSize="3.3098083333333332" effects="">
    
  </appearance>
  
</annotation>
<annotation id="annotation_4198475333" type="text" style="popup" log_data="a-type=1&amp;a-id=annotation_4198475333&amp;a-v=_NRpK5HdGmM&amp;ei=LdALXJPPLMXnigTZlabACg&amp;xble=1" itct="">
  <TEXT>Awesome. Made it with time to spare. The candy would eventually raise this balance lift, locking you out of the gem if you&#39;re not fast enough.</TEXT>
  <segment>
    <movingRegion type="rect">
      <rectRegion x="16.95700" y="89.29600" w="63.43200" h="10.85200" t="1:48.000"/>
      <rectRegion x="16.95700" y="89.29600" w="63.43200" h="10.85200" t="1:54.000"/>
    </movingRegion>
  </segment>
  <appearance bgAlpha="0.600000023842" bgColor="0" fgColor="16777215" textSize="3.3098083333333332" effects="">
    
  </appearance>
  
</annotation>
<annotation id="annotation_4205204139" type="text" style="popup" log_data="a-type=1&amp;a-id=annotation_4205204139&amp;a-v=_NRpK5HdGmM&amp;ei=LdALXJPPLMXnigTZlabACg&amp;xble=1" itct="">
  <TEXT>And, it&#39;s the same idea here with this timer switch, except you get 24 seconds this time, and the path through the spiky area is quite different.</TEXT>
  <segment>
    <movingRegion type="rect">
      <rectRegion x="18.06700" y="89.29600" w="63.90700" h="10.85200" t="4:22.000"/>
      <rectRegion x="18.06700" y="89.29600" w="63.90700" h="10.85200" t="4:28.000"/>
    </movingRegion>
  </segment>
  <appearance bgAlpha="0.600000023842" bgColor="0" fgColor="16777215" textSize="3.3098083333333332" effects="">
    
  </appearance>
  
</annotation>
<annotation id="annotation_444045619" type="text" style="popup" log_data="a-type=1&amp;a-id=annotation_444045619&amp;a-v=_NRpK5HdGmM&amp;ei=LdALXJPPLMXnigTZlabACg&amp;xble=1" itct="">
  <TEXT>If you&#39;re quick, you can try going this way to get past the revoluting boxes faster.</TEXT>
  <segment>
    <movingRegion type="rect">
      <rectRegion x="14.26300" y="93.52100" w="69.77100" h="6.62700" t="7:00.000"/>
      <rectRegion x="14.26300" y="93.52100" w="69.77100" h="6.62700" t="7:04.000"/>
    </movingRegion>
  </segment>
  <appearance bgAlpha="0.600000023842" bgColor="0" fgColor="16777215" textSize="3.3098083333333332" effects="">
    
  </appearance>
  
</annotation>
<annotation id="annotation_478761907" type="text" style="popup" log_data="a-type=1&amp;a-id=annotation_478761907&amp;a-v=_NRpK5HdGmM&amp;ei=LdALXJPPLMXnigTZlabACg&amp;xble=1" itct="">
  <TEXT>With the blue gates open, we can access a new path here.</TEXT>
  <segment>
    <movingRegion type="rect">
      <rectRegion x="23.93000" y="93.52100" w="52.65500" h="6.62000" t="4:17.019"/>
      <rectRegion x="23.93000" y="93.52100" w="52.65500" h="6.62000" t="4:21.000"/>
    </movingRegion>
  </segment>
  <appearance bgAlpha="0.600000023842" bgColor="0" fgColor="16777215" textSize="3.3098083333333332" effects="">
    
  </appearance>
  
</annotation>
<annotation id="annotation_494314833" type="text" style="popup" log_data="a-type=1&amp;a-id=annotation_494314833&amp;a-v=_NRpK5HdGmM&amp;ei=LdALXJPPLMXnigTZlabACg&amp;xble=1" itct="">
  <TEXT>Now, once you hit the switch, the candy above will start rolling down the chute on the left, and you gotta race it, because if &quot;You&#39;re too slow!&quot;, you&#39;ll miss out on a gem!</TEXT>
  <segment>
    <movingRegion type="rect">
      <rectRegion x="12.67800" y="89.29600" w="74.05000" h="10.85200" t="0:26.955"/>
      <rectRegion x="12.67800" y="89.29600" w="74.05000" h="10.85200" t="0:33.000"/>
    </movingRegion>
  </segment>
  <appearance bgAlpha="0.600000023842" bgColor="0" fgColor="16777215" textSize="3.3098083333333332" effects="">
    
  </appearance>
  
</annotation>
<annotation id="annotation_554579297" type="text" style="popup" log_data="a-type=1&amp;a-id=annotation_554579297&amp;a-v=_NRpK5HdGmM&amp;ei=LdALXJPPLMXnigTZlabACg&amp;xble=1" itct="">
  <TEXT>Clearing 3-C doesn&#39;t unlock any new levels. Now, neither 4-3 nor 4-A got any votes, so... I&#39;ll play 4-3 next, just so there&#39;s still some sort of choice for the next vote, since 4-A won&#39;t unlock any new levels either. Let&#39;s go, Mira!</TEXT>
  <segment>
    <movingRegion type="rect">
      <rectRegion x="1.10900" y="89.29600" w="97.35300" h="10.85900" t="2:16.500"/>
      <rectRegion x="1.10900" y="89.29600" w="97.35300" h="10.85900" t="2:24.500"/>
    </movingRegion>
  </segment>
  <appearance bgAlpha="0.600000023842" bgColor="0" fgColor="16777215" textSize="3.3098083333333332" effects="">
    
  </appearance>
  
</annotation>
<annotation id="annotation_578298009" type="text" style="popup" log_data="a-type=1&amp;a-id=annotation_578298009&amp;a-v=_NRpK5HdGmM&amp;ei=LdALXJPPLMXnigTZlabACg&amp;xble=1" itct="">
  <TEXT>Awesome. Yeah, the rolling candy hits that timer switch, and once that happens, you&#39;ve only got 5 seconds to get through the gate for this gem. Okay, now we can relax for the moment and attack duders.</TEXT>
  <segment>
    <movingRegion type="rect">
      <rectRegion x="4.59600" y="89.29600" w="91.80000" h="10.85200" t="0:43.500"/>
      <rectRegion x="4.59600" y="89.29600" w="91.80000" h="10.85200" t="0:50.500"/>
    </movingRegion>
  </segment>
  <appearance bgAlpha="0.600000023842" bgColor="0" fgColor="16777215" textSize="3.3098083333333332" effects="">
    
  </appearance>
  
</annotation>
<annotation id="annotation_795793309" type="text" style="popup" log_data="a-type=1&amp;a-id=annotation_795793309&amp;a-v=_NRpK5HdGmM&amp;ei=LdALXJPPLMXnigTZlabACg&amp;xble=1" itct="">
  <TEXT>2 votes for 4-1 with Mira (already done), 0 votes for 4-3, 0 votes for 4-A, and 7 votes for 3-C! Wow, 3-C got it unanimously!</TEXT>
  <segment>
    <movingRegion type="rect">
      <rectRegion x="21.55300" y="88.73200" w="56.14100" h="11.40800" t="0:05.500"/>
      <rectRegion x="21.55300" y="88.73200" w="56.14100" h="11.40800" t="0:11.500"/>
    </movingRegion>
  </segment>
  <appearance bgAlpha="0.600000023842" bgColor="0" fgColor="16777215" textSize="3.3098083333333332" effects="">
    
  </appearance>
  
</annotation>
<annotation id="annotation_863338727" type="text" style="popup" log_data="a-type=1&amp;a-id=annotation_863338727&amp;a-v=_NRpK5HdGmM&amp;ei=LdALXJPPLMXnigTZlabACg&amp;xble=1" itct="">
  <TEXT>Okay, here we go! Now, instead of going right and up from that switch, take this path down here, as it&#39;s much faster. WARNING: DON&#39;T hit the orange timer switch along the way, as it&#39;ll negate the red one and ruin everything!</TEXT>
  <segment>
    <movingRegion type="rect">
      <rectRegion x="0.31700" y="18.87300" w="99.36600" h="10.85900" t="5:15.500"/>
      <rectRegion x="0.31700" y="18.87300" w="99.36600" h="10.85900" t="5:23.500"/>
    </movingRegion>
  </segment>
  <appearance bgAlpha="0.600000023842" bgColor="0" fgColor="16777215" textSize="3.3098083333333332" effects="">
    
  </appearance>
  
</annotation>
<annotation id="annotation_863874657" type="text" style="popup" log_data="a-type=1&amp;a-id=annotation_863874657&amp;a-v=_NRpK5HdGmM&amp;ei=LdALXJPPLMXnigTZlabACg&amp;xble=1" itct="">
  <TEXT>Okay, this level introduces a new feature-- the red timer switch. It works just like the orange ones, but it opens up red timer gates for its duration, and...</TEXT>
  <segment>
    <movingRegion type="rect">
      <rectRegion x="15.84800" y="89.29600" w="67.07700" h="10.85200" t="2:34.500"/>
      <rectRegion x="15.84800" y="89.29600" w="67.07700" h="10.85200" t="2:40.500"/>
    </movingRegion>
  </segment>
  <appearance bgAlpha="0.600000023842" bgColor="0" fgColor="16777215" textSize="3.3098083333333332" effects="">
    
  </appearance>
  
</annotation>
<annotation id="annotation_871237123" type="text" style="popup" log_data="a-type=1&amp;a-id=annotation_871237123&amp;a-v=_NRpK5HdGmM&amp;ei=LdALXJPPLMXnigTZlabACg&amp;xble=1" itct="">
  <TEXT>6743 is pretty good. However, I&#39;m pretty sure 7000 is reachable.</TEXT>
  <segment>
    <movingRegion type="rect">
      <rectRegion x="21.87000" y="0.00000" w="56.93400" h="6.62700" t="7:22.500"/>
      <rectRegion x="21.87000" y="0.00000" w="56.93400" h="6.62700" t="7:26.500"/>
    </movingRegion>
  </segment>
  <appearance bgAlpha="0.600000023842" bgColor="0" fgColor="16777215" textSize="3.3098083333333332" effects="">
    
  </appearance>
  
</annotation>
<annotation id="annotation_885305549" type="text" style="popup" log_data="a-type=1&amp;a-id=annotation_885305549&amp;a-v=_NRpK5HdGmM&amp;ei=LdALXJPPLMXnigTZlabACg&amp;xble=1" itct="">
  <TEXT>Triple combo!
(3 kills, 3000 points)</TEXT>
  <segment>
    <movingRegion type="rect">
      <rectRegion x="80.03200" y="12.67600" w="20.00900" h="11.13400" t="0:55.500"/>
      <rectRegion x="80.03200" y="12.67600" w="20.00900" h="11.13400" t="0:59.500"/>
    </movingRegion>
  </segment>
  <appearance bgAlpha="0.600000023842" bgColor="0" fgColor="16777215" textSize="3.3098083333333332" effects="">
    
  </appearance>
  
</annotation>
<annotation id="annotation_939752347" type="text" style="popup" log_data="a-type=1&amp;a-id=annotation_939752347&amp;a-v=_NRpK5HdGmM&amp;ei=LdALXJPPLMXnigTZlabACg&amp;xble=1" itct="">
  <TEXT>Huzzah! Now, just kill this final pair of black slimes and hit the moon switch.</TEXT>
  <segment>
    <movingRegion type="rect">
      <rectRegion x="16.48200" y="93.52100" w="67.39400" h="6.62700" t="5:24.027"/>
      <rectRegion x="16.48200" y="93.52100" w="67.39400" h="6.62700" t="5:28.000"/>
    </movingRegion>
  </segment>
  <appearance bgAlpha="0.600000023842" bgColor="0" fgColor="16777215" textSize="3.3098083333333332" effects="">
    
  </appearance>
  
</annotation>
<annotation id="annotation_957770007" type="text" style="popup" log_data="a-type=1&amp;a-id=annotation_957770007&amp;a-v=_NRpK5HdGmM&amp;ei=LdALXJPPLMXnigTZlabACg&amp;xble=1" itct="">
  <TEXT>Hyper combo!
(5 kills, 7500 points)</TEXT>
  <segment>
    <movingRegion type="rect">
      <rectRegion x="80.19000" y="13.80300" w="19.85000" h="10.85200" t="3:31.000"/>
      <rectRegion x="80.19000" y="13.80300" w="19.85000" h="10.85200" t="3:35.000"/>
    </movingRegion>
  </segment>
  <appearance bgAlpha="0.600000023842" bgColor="0" fgColor="16777215" textSize="3.3098083333333332" effects="">
    
  </appearance>
  
</annotation></annotations></document>