<?xml version="1.0" encoding="UTF-8" ?><document><annotations itct="CAAQwOYBIhMI9ea1qOGz3wIVieycCh1PsAYsKPgdMgJpdkjWoaTDvIyo958B">
<annotation id="annotation_107788" type="text" style="popup" log_data="a-id=annotation_107788&amp;a-type=1&amp;xble=1&amp;a-v=n-6gY8hpENY&amp;ei=O1keXLXdA4nZ8wTP4JrgAg" itct="CAEQs-UBGP___________wEiEwj15rWo4bPfAhWJ7JwKHU-wBiwo-B0yAml2SNahpMO8jKj3nwE">
  <TEXT>Moving right along, it is time for another on-foot stage! This time with lots of bars and saloons... Yay? XD</TEXT>
  <segment>
    <movingRegion type="rect">
      <rectRegion x="65.15600" y="0.00000" w="34.84400" h="16.11100" t="0:00:06.5"/>
      <rectRegion x="65.15600" y="0.00000" w="34.84400" h="16.11100" t="0:00:11.5"/>
    </movingRegion>
  </segment>
  <appearance bgAlpha="0.800000011921" bgColor="11847903" fgColor="1710618" textSize="3.6107" effects="">
    
  </appearance>
  
</annotation>
<annotation id="annotation_152635" type="text" style="popup" log_data="a-id=annotation_152635&amp;a-type=1&amp;xble=1&amp;a-v=n-6gY8hpENY&amp;ei=O1keXLXdA4nZ8wTP4JrgAg" itct="CAIQs-UBGP___________wEiEwj15rWo4bPfAhWJ7JwKHU-wBiwo-B0yAml2SNahpMO8jKj3nwE">
  <TEXT>...and yes... he DOES proceed to wear that hat for the rest of the game! ...Awesome. XD</TEXT>
  <segment>
    <movingRegion type="rect">
      <rectRegion x="69.84400" y="0.00000" w="30.15600" h="16.11100" t="0:06:47.7"/>
      <rectRegion x="69.84400" y="0.00000" w="30.15600" h="16.11100" t="0:06:52.7"/>
    </movingRegion>
  </segment>
  <appearance bgAlpha="0.800000011921" bgColor="11847903" fgColor="1710618" textSize="3.6107" effects="">
    
  </appearance>
  
</annotation>
<annotation id="annotation_262908" type="text" style="popup" log_data="a-id=annotation_262908&amp;a-type=1&amp;xble=1&amp;a-v=n-6gY8hpENY&amp;ei=O1keXLXdA4nZ8wTP4JrgAg" itct="CAMQs-UBGP___________wEiEwj15rWo4bPfAhWJ7JwKHU-wBiwo-B0yAml2SNahpMO8jKj3nwE">
  <TEXT>You are safe from the lanterns if you hang from the chandelier, but you have to worry about dodging the bombs. Kill off the left enemy first to make the remaining battle a breeze!</TEXT>
  <segment>
    <movingRegion type="rect">
      <rectRegion x="55.62500" y="0.00000" w="44.37500" h="20.55600" t="0:02:55.8"/>
      <rectRegion x="55.62500" y="0.00000" w="44.37500" h="20.55600" t="0:03:02.8"/>
    </movingRegion>
  </segment>
  <appearance bgAlpha="0.800000011921" bgColor="11847903" fgColor="1710618" textSize="3.6107" effects="">
    
  </appearance>
  
</annotation>
<annotation id="annotation_268073" type="text" style="popup" log_data="a-id=annotation_268073&amp;a-type=1&amp;xble=1&amp;a-v=n-6gY8hpENY&amp;ei=O1keXLXdA4nZ8wTP4JrgAg" itct="CAQQs-UBGP___________wEiEwj15rWo4bPfAhWJ7JwKHU-wBiwo-B0yAml2SNahpMO8jKj3nwE">
  <TEXT>Beware of low beams as well! There may not be any low bridges in this stage, but the beams are just as deadly!</TEXT>
  <segment>
    <movingRegion type="rect">
      <rectRegion x="61.09400" y="0.00000" w="38.90600" h="16.11100" t="0:04:50.9"/>
      <rectRegion x="61.09400" y="0.00000" w="38.90600" h="16.11100" t="0:04:56.9"/>
    </movingRegion>
  </segment>
  <appearance bgAlpha="0.800000011921" bgColor="11847903" fgColor="1710618" textSize="3.6107" effects="">
    
  </appearance>
  
</annotation>
<annotation id="annotation_309121" type="text" style="popup" log_data="a-id=annotation_309121&amp;a-type=1&amp;xble=1&amp;a-v=n-6gY8hpENY&amp;ei=O1keXLXdA4nZ8wTP4JrgAg" itct="CAUQs-UBGP___________wEiEwj15rWo4bPfAhWJ7JwKHU-wBiwo-B0yAml2SNahpMO8jKj3nwE">
  <TEXT>He would be much easier with a second player handy, but alas, going solo against him is semi-suicidal. If he positions himself right, there is no escaping that whip in one piece!</TEXT>
  <segment>
    <movingRegion type="rect">
      <rectRegion x="64.53100" y="0.00000" w="35.46900" h="25.00000" t="0:05:33.0"/>
      <rectRegion x="64.53100" y="0.00000" w="35.46900" h="25.00000" t="0:05:41.0"/>
    </movingRegion>
  </segment>
  <appearance bgAlpha="0.800000011921" bgColor="11847903" fgColor="1710618" textSize="3.6107" effects="">
    
  </appearance>
  
</annotation>
<annotation id="annotation_328216" type="text" style="popup" log_data="a-id=annotation_328216&amp;a-type=1&amp;xble=1&amp;a-v=n-6gY8hpENY&amp;ei=O1keXLXdA4nZ8wTP4JrgAg" itct="CAYQs-UBGP___________wEiEwj15rWo4bPfAhWJ7JwKHU-wBiwo-B0yAml2SNahpMO8jKj3nwE">
  <TEXT>In case you did not see it the first time... it shows &quot;Shoot Rider&quot; EVERY SINGLE TIME Dark Horse comes back onto the screen! XD</TEXT>
  <segment>
    <movingRegion type="rect">
      <rectRegion x="66.71900" y="0.00000" w="33.28100" h="20.55600" t="0:02:09.0"/>
      <rectRegion x="66.71900" y="0.00000" w="33.28100" h="20.55600" t="0:02:16.0"/>
    </movingRegion>
  </segment>
  <appearance bgAlpha="0.800000011921" bgColor="11847903" fgColor="1710618" textSize="3.6107" effects="">
    
  </appearance>
  
</annotation>
<annotation id="annotation_404052" type="text" style="popup" log_data="a-id=annotation_404052&amp;a-type=1&amp;xble=1&amp;a-v=n-6gY8hpENY&amp;ei=O1keXLXdA4nZ8wTP4JrgAg" itct="CAcQs-UBGP___________wEiEwj15rWo4bPfAhWJ7JwKHU-wBiwo-B0yAml2SNahpMO8jKj3nwE">
  <TEXT>Best part of the Arcade version right here! Cormano totally steals El Greco&#39;s hat! Only Cormano will do this, and this only happens in the Arcade!</TEXT>
  <segment>
    <movingRegion type="rect">
      <rectRegion x="0.00000" y="0.00000" w="37.50000" h="20.55600" t="0:06:37.8"/>
      <rectRegion x="0.00000" y="0.00000" w="37.50000" h="20.55600" t="0:06:45.8"/>
    </movingRegion>
  </segment>
  <appearance bgAlpha="0.800000011921" bgColor="13369344" fgColor="16777215" textSize="3.6107" effects="">
    
  </appearance>
  
</annotation>
<annotation id="annotation_446929" type="text" style="popup" log_data="a-id=annotation_446929&amp;a-type=1&amp;xble=1&amp;a-v=n-6gY8hpENY&amp;ei=O1keXLXdA4nZ8wTP4JrgAg" itct="CAgQs-UBGP___________wEiEwj15rWo4bPfAhWJ7JwKHU-wBiwo-B0yAml2SNahpMO8jKj3nwE">
  <TEXT>More Bonus Game fun! This is the second and last one in the game, and for some reason it seems easier than the first one on the Arcade version.</TEXT>
  <segment>
    <movingRegion type="rect">
      <rectRegion x="63.75000" y="0.00000" w="36.25000" h="20.55600" t="0:06:56.4"/>
      <rectRegion x="63.75000" y="0.00000" w="36.25000" h="20.55600" t="0:07:03.4"/>
    </movingRegion>
  </segment>
  <appearance bgAlpha="0.800000011921" bgColor="11847903" fgColor="1710618" textSize="3.6107" effects="">
    
  </appearance>
  
</annotation>
<annotation id="annotation_470153" type="text" style="popup" log_data="a-id=annotation_470153&amp;a-type=1&amp;xble=1&amp;a-v=n-6gY8hpENY&amp;ei=O1keXLXdA4nZ8wTP4JrgAg" itct="CAkQs-UBGP___________wEiEwj15rWo4bPfAhWJ7JwKHU-wBiwo-B0yAml2SNahpMO8jKj3nwE">
  <TEXT>Now that the short stage is done... Onto the boss! He is borderline cheap since you cannot guide his jumps as easily as on the SNES port.</TEXT>
  <segment>
    <movingRegion type="rect">
      <rectRegion x="63.59400" y="0.00000" w="36.40600" h="20.55600" t="0:05:23.3"/>
      <rectRegion x="63.59400" y="0.00000" w="36.40600" h="20.55600" t="0:05:29.3"/>
    </movingRegion>
  </segment>
  <appearance bgAlpha="0.800000011921" bgColor="11847903" fgColor="1710618" textSize="3.6107" effects="">
    
  </appearance>
  
</annotation>
<annotation id="annotation_480574" type="text" style="popup" log_data="a-id=annotation_480574&amp;a-type=1&amp;xble=1&amp;a-v=n-6gY8hpENY&amp;ei=O1keXLXdA4nZ8wTP4JrgAg" itct="CAoQs-UBGP___________wEiEwj15rWo4bPfAhWJ7JwKHU-wBiwo-B0yAml2SNahpMO8jKj3nwE">
  <TEXT>...Like so. What a pest... =x.x=;</TEXT>
  <segment>
    <movingRegion type="rect">
      <rectRegion x="68.43800" y="0.00000" w="31.56300" h="7.22200" t="0:05:46.6"/>
      <rectRegion x="68.43800" y="0.00000" w="31.56300" h="7.22200" t="0:05:51.6"/>
    </movingRegion>
  </segment>
  <appearance bgAlpha="0.800000011921" bgColor="11847903" fgColor="1710618" textSize="3.6107" effects="">
    
  </appearance>
  
</annotation>
<annotation id="annotation_565951" type="text" style="popup" log_data="a-id=annotation_565951&amp;a-type=1&amp;xble=1&amp;a-v=n-6gY8hpENY&amp;ei=O1keXLXdA4nZ8wTP4JrgAg" itct="">
  <TEXT>I may have gotten a Perfect on this one if my fingers did not get ahead of themselves a couple of times. Oh well~ XD</TEXT>
  <segment>
    <movingRegion type="rect">
      <rectRegion x="59.21900" y="0.00000" w="40.78100" h="16.11100" t="0:07:36.6"/>
      <rectRegion x="59.21900" y="0.00000" w="40.78100" h="16.11100" t="0:07:42.6"/>
    </movingRegion>
  </segment>
  <appearance bgAlpha="0.800000011921" bgColor="11847903" fgColor="1710618" textSize="3.6107" effects="">
    
  </appearance>
  
</annotation>
<annotation id="annotation_662937" type="text" style="popup" log_data="a-id=annotation_662937&amp;a-type=1&amp;xble=1&amp;a-v=n-6gY8hpENY&amp;ei=O1keXLXdA4nZ8wTP4JrgAg" itct="">
  <TEXT>Stage 5 brings us to a moving train stage! Watch out, the baddies try lots of dirty tricks here, including blowing up the train car connections!</TEXT>
  <segment>
    <movingRegion type="rect">
      <rectRegion x="64.53100" y="0.00000" w="35.46900" h="20.55600" t="0:04:23.4"/>
      <rectRegion x="64.53100" y="0.00000" w="35.46900" h="20.55600" t="0:04:30.4"/>
    </movingRegion>
  </segment>
  <appearance bgAlpha="0.800000011921" bgColor="11847903" fgColor="1710618" textSize="3.6107" effects="">
    
  </appearance>
  
</annotation><annotation author="PinkKittyRose" id="annotation_707257" log_data="a-id=annotation_707257&amp;a-type=2&amp;xble=1&amp;a-v=n-6gY8hpENY&amp;ei=O1keXLXdA4nZ8wTP4JrgAg" style="speech" type="text"><TEXT>Hmm... That's a nice hat! I think I'll keep it!</TEXT><segment><movingRegion type="anchored"><anchoredRegion d="0" h="13.3330001831" sx="77.03099823" sy="27.5" t="0:06:41.6" w="23.125" x="61.71900177" y="8.88899993896" /><anchoredRegion d="0" h="13.3330001831" sx="77.03099823" sy="27.5" t="0:06:44.6" w="23.125" x="61.71900177" y="8.88899993896" /></movingRegion></segment><appearance bgAlpha="0.800000011921" bgColor="11847903" borderAlpha="0.20000000298" borderColor="0" borderWidth="0" fgColor="1710618" gloss="70" highlightFontColor="11847903" highlightWidth="3" /></annotation>
<annotation id="annotation_757191" type="text" style="popup" log_data="a-id=annotation_757191&amp;a-type=1&amp;xble=1&amp;a-v=n-6gY8hpENY&amp;ei=O1keXLXdA4nZ8wTP4JrgAg" itct="">
  <TEXT>Alright, move along. Nothing to see here. There is definitely nothing of interest at this current time so just fast forward a few seconds and everything will be better. Move along now people we are not here to watch what is going on at this current time. (In case you have not guessed, I heavily dis-like this scene... I would have used a fast-forward button had the emulator I was using had one handy that did not seem to break the game entirely. Yes, I did try... It would not go back down to regular speed. XD)</TEXT>
  <segment>
    <movingRegion type="rect">
      <rectRegion x="22.34400" y="18.88900" w="55.00000" h="42.77800" t="0:03:42.4"/>
      <rectRegion x="22.34400" y="18.88900" w="55.00000" h="42.77800" t="0:03:59.4"/>
    </movingRegion>
  </segment>
  <appearance bgAlpha="0.800000011921" bgColor="13369344" fgColor="16777215" textSize="3.6107" effects="">
    
  </appearance>
  
</annotation>
<annotation id="annotation_859737" type="text" style="popup" log_data="a-id=annotation_859737&amp;a-type=1&amp;xble=1&amp;a-v=n-6gY8hpENY&amp;ei=O1keXLXdA4nZ8wTP4JrgAg" itct="">
  <TEXT>&quot;El Greco&quot;, eh? Suddenly I have a craving for pizza... XD</TEXT>
  <segment>
    <movingRegion type="rect">
      <rectRegion x="71.71900" y="0.00000" w="28.28100" h="11.66700" t="0:04:15.6"/>
      <rectRegion x="71.71900" y="0.00000" w="28.28100" h="11.66700" t="0:04:20.6"/>
    </movingRegion>
  </segment>
  <appearance bgAlpha="0.800000011921" bgColor="11847903" fgColor="1710618" textSize="3.6107" effects="">
    
  </appearance>
  
</annotation>
<annotation id="annotation_89293" type="text" style="popup" log_data="a-id=annotation_89293&amp;a-type=1&amp;xble=1&amp;a-v=n-6gY8hpENY&amp;ei=O1keXLXdA4nZ8wTP4JrgAg" itct="">
  <TEXT>Stage 4 is... very quick. It is only a boss, and this boss only has two minions! The battle can be tricky though... You have to dodge two very different projectiles constantly!</TEXT>
  <segment>
    <movingRegion type="rect">
      <rectRegion x="56.87500" y="0.00000" w="43.12500" h="20.55600" t="0:02:47.7"/>
      <rectRegion x="56.87500" y="0.00000" w="43.12500" h="20.55600" t="0:02:54.7"/>
    </movingRegion>
  </segment>
  <appearance bgAlpha="0.800000011921" bgColor="11847903" fgColor="1710618" textSize="3.6107" effects="">
    
  </appearance>
  
</annotation>
<annotation id="annotation_973561" type="text" style="popup" log_data="a-id=annotation_973561&amp;a-type=1&amp;xble=1&amp;a-v=n-6gY8hpENY&amp;ei=O1keXLXdA4nZ8wTP4JrgAg" itct="">
  <TEXT>Cormano sure is having a lot to drink... I do hope he does not get impaired from all of that... XD</TEXT>
  <segment>
    <movingRegion type="rect">
      <rectRegion x="68.12500" y="0.00000" w="31.87500" h="16.11100" t="0:01:11.4"/>
      <rectRegion x="68.12500" y="0.00000" w="31.87500" h="16.11100" t="0:01:16.4"/>
    </movingRegion>
  </segment>
  <appearance bgAlpha="0.800000011921" bgColor="11847903" fgColor="1710618" textSize="3.6107" effects="">
    
  </appearance>
  
</annotation>
<annotation id="annotation_988938" type="text" style="popup" log_data="a-id=annotation_988938&amp;a-type=1&amp;xble=1&amp;a-v=n-6gY8hpENY&amp;ei=O1keXLXdA4nZ8wTP4JrgAg" itct="">
  <TEXT>*gasp* Dark Horse is keeping Cormano from further alcohol consumption! Cormano shall never allow this! XD</TEXT>
  <segment>
    <movingRegion type="rect">
      <rectRegion x="62.50000" y="0.00000" w="37.50000" h="16.11100" t="0:01:55.7"/>
      <rectRegion x="62.50000" y="0.00000" w="37.50000" h="16.11100" t="0:02:00.7"/>
    </movingRegion>
  </segment>
  <appearance bgAlpha="0.800000011921" bgColor="11847903" fgColor="1710618" textSize="3.6107" effects="">
    
  </appearance>
  
</annotation>
<annotation id="channel:4f11a7d4-68b0-4a05-bb3a-c9e11ec568dd" style="branding" type="branding"
            log_data="a-ch=UClrsfaRb2lKZQOyekLJODqA&amp;a-type=10&amp;ei=O1keXLXdA4nZ8wTP4JrgAg&amp;link-id=UClrsfaRb2lKZQOyekLJODqA&amp;a-v=n-6gY8hpENY&amp;l-class=3&amp;a-id=4f11a7d4-68b0-4a05-bb3a-c9e11ec568dd&amp;xble=0">
  <data>{&quot;image_width&quot;:40,&quot;end_ms&quot;:467000,&quot;session_data&quot;:{&quot;src_vid&quot;:&quot;n-6gY8hpENY&quot;,&quot;annotation_id&quot;:&quot;4f11a7d4-68b0-4a05-bb3a-c9e11ec568dd&quot;,&quot;feature&quot;:&quot;iv&quot;,&quot;itct&quot;:&quot;CAsQ8zcY____________ASITCPXmtajhs98CFYnsnAodT7AGLCj4HTICaXZI1qGkw7yMqPefAQ&quot;,&quot;ei&quot;:&quot;O1keXLXdA4nZ8wTP4JrgAg&quot;},&quot;standalone_subscribe_button_data&quot;:{&quot;classic&quot;:true,&quot;unsubscribeCount&quot;:&quot;21K&quot;,&quot;subscribeText&quot;:&quot;Subscribe&quot;,&quot;subscribeCount&quot;:&quot;21K&quot;,&quot;unsubscribeText&quot;:&quot;Subscribed&quot;,&quot;subscribed&quot;:false,&quot;enabled&quot;:false,&quot;feature&quot;:&quot;iv&quot;,&quot;signinUrl&quot;:&quot;https:\/\/accounts.google.com\/ServiceLogin?continue=http%3A%2F%2Fwww.youtube.com%2Fsignin%3Fapp%3Ddesktop%26next%3Dhttps%253A%252F%252Fwww.youtube.com%252Fuser%252FPinkKittyRose%26continue_action%3DQUFFLUhqbVFGdFRaTy03Q1F4dzZaMW55WlNRdkh3YUFKZ3xBQ3Jtc0tuWHVISzhTOVhNMndIeW9wVVc3MWNKckdISGdQaHU3VWwyTWhWTDdwbndGZENNalpLeUk4X2Zja1RxTUZpd1duQW5HQzRHNlpBLTJ6Zkx0RFhtdDREQUFtcnZGTWE3al9pQ2pKMklKbGxnTWkwbUZwNlpPUFpVZWoxX252VVZOMjBSZGN0LVNvREZkeXAyY3cyOWRSRTRjVHBQX2loc1NFcG1PQ3RGM0U2MkMtZ2VBclpGTWdyZ29JTzRIcnJoX1dDSW92X3I1TGlzUDV6QXpNcTdVT253azhTSkpWU0lqdmNJYlREOXRnM0J5ZFBvSEdV%26hl%3Den%26action_handle_signin%3Dtrue%26feature%3Div\u0026passive=true\u0026uilel=3\u0026hl=en\u0026service=youtube&quot;},&quot;use_standalone_subscribe_button&quot;:true,&quot;start_ms&quot;:5000,&quot;channel_id&quot;:&quot;UClrsfaRb2lKZQOyekLJODqA&quot;,&quot;image_type&quot;:1,&quot;subscription_token&quot;:[&quot;&quot;,&quot;&quot;],&quot;image_url&quot;:&quot;https:\/\/i.ytimg.com\/an\/lrsfaRb2lKZQOyekLJODqA\/featured_channel.jpg?v=5a1a2956&quot;,&quot;channel_name&quot;:&quot;PinkKittyRose&quot;,&quot;image_height&quot;:40,&quot;num_subscribers&quot;:&quot;21276&quot;,&quot;is_mobile&quot;:false}</data>
  <segment/>
  <action trigger="click" type="openUrl">
    <url type="hyperlink" target="new" value="https://www.youtube.com/user/PinkKittyRose"/>
  </action>
</annotation></annotations></document>