<?xml version="1.0" encoding="UTF-8" ?><document><annotations itct="CAAQwOYBIhMIu5DX0ark3wIVlKrBCh0aEgGmKPgdMgJpdkj8rvaL6ebypJwB">
<annotation id="annotation_299562" type="text" style="popup" log_data="xble=1&amp;a-id=annotation_299562&amp;l-class=5&amp;a-v=nEnLNpF9l3w&amp;ei=kNA3XLuIMpTVhgaapISwCg&amp;a-type=1&amp;link=http%3A%2F%2Fwww.youtube.com%2Fsubscription_center%3Fadd_user%3Dgamexplain" itct="CAEQs-UBGP___________wEiEwi7kNfRquTfAhWUqsEKHRoSAaYo-B0yAml2SPyu9ovp5vKknAE">
  <TEXT>Subscribe!</TEXT>
  <segment>
    <movingRegion type="rect">
      <rectRegion x="38.75000" y="0.00000" w="19.06300" h="9.44400" t="0:00:03.5"/>
      <rectRegion x="38.75000" y="0.00000" w="19.06300" h="9.44400" t="0:09:23.2"/>
    </movingRegion>
  </segment>
  <appearance bgAlpha="0.25" bgColor="0" fgColor="16777215" textSize="3.9116" effects="textdropshadow">
    <padding top="2.34696006775" left="1.32016503811" bottom="2.34696006775" right="1.76022005081"/>
  </appearance>
  
  <action type="openUrl" trigger="click">
    <url target="new" value="https://www.youtube.com/subscription_center?add_user=gamexplain&amp;annotation_id=annotation_299562&amp;ei=kNA3XLuIMpTVhgaapISwCg&amp;feature=iv&amp;src_vid=nEnLNpF9l3w" link_class="5"/>
  </action>

</annotation>
<annotation id="annotation_510201" type="text" style="highlightText" logable="false" itct="">
  
  <segment spaceRelative="annotation_852468">
    <movingRegion type="rect">
      <rectRegion x="0.00000" y="29.72200" w="25.00000" h="6.11100" t="never"/>
      <rectRegion x="0.00000" y="29.72200" w="25.00000" h="6.11100" t="never"/>
    </movingRegion>
  </segment>
  <appearance bgAlpha="0" textSize="3.9116" highlightFontColor="15921906"/>
  <trigger>
    <condition ref="annotation_852468" state="rollOver"/>
  </trigger>
</annotation>

<annotation id="annotation_551305" type="text" style="popup" log_data="xble=1&amp;a-id=annotation_551305&amp;l-class=5&amp;a-v=nEnLNpF9l3w&amp;ei=kNA3XLuIMpTVhgaapISwCg&amp;a-type=1&amp;link=http%3A%2F%2Fwww.youtube.com%2Fsubscription_center%3Fadd_user%3Dgamexplain" itct="CAIQs-UBGP___________wEiEwi7kNfRquTfAhWUqsEKHRoSAaYo-B0yAml2SPyu9ovp5vKknAE">
  <TEXT>Click here to subscribe to GameXplain for more awesome videos!</TEXT>
  <segment>
    <movingRegion type="rect">
      <rectRegion x="26.09400" y="11.11100" w="43.43800" h="14.44400" t="0:09:13.5"/>
      <rectRegion x="26.09400" y="11.11100" w="43.43800" h="14.44400" t="0:09:23.2"/>
    </movingRegion>
  </segment>
  <appearance bgAlpha="0.25" bgColor="0" fgColor="16777215" textSize="3.9116" effects="textdropshadow">
    <padding top="2.34696006775" left="1.32016503811" bottom="2.34696006775" right="1.76022005081"/>
  </appearance>
  
  <action type="openUrl" trigger="click">
    <url target="new" value="https://www.youtube.com/subscription_center?add_user=gamexplain&amp;annotation_id=annotation_551305&amp;ei=kNA3XLuIMpTVhgaapISwCg&amp;feature=iv&amp;src_vid=nEnLNpF9l3w" link_class="5"/>
  </action>

</annotation>
<annotation id="annotation_565224" type="text" style="popup" log_data="ei=kNA3XLuIMpTVhgaapISwCg&amp;xble=1&amp;a-type=1&amp;a-id=annotation_565224&amp;a-v=nEnLNpF9l3w" itct="CAMQs-UBGP___________wEiEwi7kNfRquTfAhWUqsEKHRoSAaYo-B0yAml2SPyu9ovp5vKknAE">
  <TEXT>Multiplayer</TEXT>
  <segment>
    <movingRegion type="rect">
      <rectRegion x="28.12500" y="19.44400" w="42.65600" h="20.00000" t="0:09:11.3"/>
      <rectRegion x="28.12500" y="19.44400" w="42.65600" h="20.00000" t="0:09:15.7"/>
    </movingRegion>
  </segment>
  <appearance bgAlpha="0.600000023842" bgColor="0" fgColor="16777215" textSize="8.42496666666667" effects="textdropshadow">
    <padding top="5.05497980118" left="2.84342622757" bottom="5.05497980118" right="3.79123497009"/>
  </appearance>
  
</annotation>
<annotation id="annotation_852468" type="highlight" log_data="xble=1&amp;a-id=annotation_852468&amp;l-class=3&amp;a-v=nEnLNpF9l3w&amp;ei=kNA3XLuIMpTVhgaapISwCg&amp;a-type=3&amp;link=http%3A%2F%2Fwww.youtube.com%2Fuser%2Fgamexplain" itct="CAQQs-UBGP___________wEiEwi7kNfRquTfAhWUqsEKHRoSAaYo-B0yAml2SPyu9ovp5vKknAE">
  <segment>
    <movingRegion type="rect">
      <rectRegion x="8.59400" y="36.11100" w="81.08600" h="30.65300" t="0:09:17.5"/>
      <rectRegion x="8.59400" y="36.11100" w="81.08600" h="30.65300" t="0:09:23.2"/>
    </movingRegion>
  </segment>
  <appearance bgColor="16777215" highlightWidth="3" borderAlpha="0.25"/>
  
  <action type="openUrl" trigger="click">
    <url target="current" value="https://www.youtube.com/user/gamexplain?annotation_id=annotation_852468&amp;ei=kNA3XLuIMpTVhgaapISwCg&amp;feature=iv&amp;src_vid=nEnLNpF9l3w" link_class="3"/>
  </action>

</annotation>

<annotation id="channel:56aa5527-0000-2093-b3f2-94eb2c08a290" style="branding" type="branding"
            log_data="xble=0&amp;a-id=56aa5527-0000-2093-b3f2-94eb2c08a290&amp;l-class=3&amp;link-id=UCfAPTv1LgeEWevG8X_6PUOQ&amp;a-v=nEnLNpF9l3w&amp;ei=kNA3XLuIMpTVhgaapISwCg&amp;a-type=10&amp;a-ch=UCfAPTv1LgeEWevG8X_6PUOQ">
  <data>{&quot;is_mobile&quot;:false,&quot;image_width&quot;:40,&quot;num_subscribers&quot;:&quot;1095884&quot;,&quot;image_height&quot;:40,&quot;channel_name&quot;:&quot;GameXplain&quot;,&quot;image_url&quot;:&quot;https:\/\/i.ytimg.com\/an\/fAPTv1LgeEWevG8X_6PUOQ\/featured_channel.jpg?v=56ad33c2&quot;,&quot;subscription_token&quot;:[&quot;&quot;,&quot;&quot;],&quot;image_type&quot;:1,&quot;channel_id&quot;:&quot;UCfAPTv1LgeEWevG8X_6PUOQ&quot;,&quot;use_standalone_subscribe_button&quot;:true,&quot;start_ms&quot;:0,&quot;end_ms&quot;:563000,&quot;session_data&quot;:{&quot;ei&quot;:&quot;kNA3XLuIMpTVhgaapISwCg&quot;,&quot;itct&quot;:&quot;CAUQ8zcY____________ASITCLuQ19Gq5N8CFZSqwQodGhIBpij4HTICaXZI_K72i-nm8qScAQ&quot;,&quot;feature&quot;:&quot;iv&quot;,&quot;annotation_id&quot;:&quot;56aa5527-0000-2093-b3f2-94eb2c08a290&quot;,&quot;src_vid&quot;:&quot;nEnLNpF9l3w&quot;},&quot;standalone_subscribe_button_data&quot;:{&quot;subscribeCount&quot;:&quot;1M&quot;,&quot;enabled&quot;:false,&quot;subscribed&quot;:false,&quot;unsubscribeText&quot;:&quot;Subscribed&quot;,&quot;subscribeText&quot;:&quot;Subscribe&quot;,&quot;unsubscribeCount&quot;:&quot;1M&quot;,&quot;classic&quot;:true,&quot;signinUrl&quot;:&quot;https:\/\/accounts.google.com\/ServiceLogin?service=youtube\u0026uilel=3\u0026hl=en\u0026passive=true\u0026continue=http%3A%2F%2Fwww.youtube.com%2Fsignin%3Ffeature%3Div%26action_handle_signin%3Dtrue%26hl%3Den%26continue_action%3DQUFFLUhqa3lESGRmY0JSTmpnZWNmYko2NTh4WTZRU2VWZ3xBQ3Jtc0tuZUdIS25VTk9pMW9JSjAyazhic2w1dlY1djBfQkxMMW5ROXY0M19zVEJYZ3Nqb1pfSnFualJJUHNTUHc0eWNFZjJ4Q3hiOG1qTWZGZXlJV3UtQl9aejhSNlZjRWpvRFY3eXYxbE5aaUM4WGw0TXhIN0NNMFhMWFMxQzhXV01VdGpuSVk3eEZUUHhTOXF4dVduc3ctLXU2OUJuM1lyRUNZMF9ocHFlWTYxUDFaQkt6WlJRMmNGbVJsenhncjV2bXBaMUVUX2laOEp6N1VSX3c5Mjd0d0laU0V4TnE0dmY4aXpKd214SWlWYmZPb0FKLXh3%26next%3Dhttps%253A%252F%252Fwww.youtube.com%252Fuser%252FGameXplain%26app%3Ddesktop&quot;,&quot;feature&quot;:&quot;iv&quot;}}</data>
  <segment/>
  <action trigger="click" type="openUrl">
    <url type="hyperlink" target="new" value="https://www.youtube.com/user/GameXplain"/>
  </action>
</annotation></annotations></document>